CHANGES.txt
LICENSE.txt
MANIFEST.in
README.md
requirements_test.txt
setup.py
sensu_plugin26/__init__.py
sensu_plugin26/check.py
sensu_plugin26/exithook.py
sensu_plugin26/handler.py
sensu_plugin26/metric.py
sensu_plugin26/plugin.py
sensu_plugin26.egg-info/PKG-INFO
sensu_plugin26.egg-info/SOURCES.txt
sensu_plugin26.egg-info/dependency_links.txt
sensu_plugin26.egg-info/requires.txt
sensu_plugin26.egg-info/top_level.txt
sensu_plugin26/test/__init__.py