Metadata-Version: 1.0
Name: sensu-plugin26
Version: 0.2.0
Summary: A framework for writing Python sensu plugins.
Home-page: http://github.com/sensu/python_sensu_plugin/
Author: S. Zachariah Sprackett
Author-email: zac@sprackett.com
License: LICENSE.txt
Platform: UNKNOWN
